README.rst
setup.py
score/__init__.py
score.ws.egg-info/PKG-INFO
score.ws.egg-info/SOURCES.txt
score.ws.egg-info/dependency_links.txt
score.ws.egg-info/namespace_packages.txt
score.ws.egg-info/not-zip-safe
score.ws.egg-info/requires.txt
score.ws.egg-info/top_level.txt
score/ws/__init__.py
score/ws/_init.py
score/ws/worker.py